{
    "created": "datetime",
    "expires_at": "datetime",
    "payment_method_preview": {
        "card": {
            "generated_from": {
                "payment_method_details": {
                    "card_present": {
                        "amount_authorized": "currency",
                        "capture_before": "datetime",
                        "offline": {
                            "stored_at": "datetime"
                        }
                    }
                }
            }
        },
        "card_present": {
            "offline": {
                "stored_at": "datetime"
            }
        }
    }
}
